.gitignore
CHANGES.rst
LICENSE.txt
Makefile
README.rst
setup.cfg
setup.py
tox.ini
Soho.egg-info/PKG-INFO
Soho.egg-info/SOURCES.txt
Soho.egg-info/dependency_links.txt
Soho.egg-info/entry_points.txt
Soho.egg-info/not-zip-safe
Soho.egg-info/requires.txt
Soho.egg-info/top_level.txt
docs/Makefile
docs/api.rst
docs/basics.rst
docs/changes.rst
docs/conf.py
docs/dev.rst
docs/index.rst
docs/installation.rst
docs/ref.rst
docs/tutorial-1-intro.rst
docs/tutorial-2-assets.rst
docs/tutorial-3-metadata.rst
docs/tutorial-4-i18n.rst
docs/tutorial.rst
docs/_build/doctrees/api.doctree
docs/_build/doctrees/basics.doctree
docs/_build/doctrees/changes.doctree
docs/_build/doctrees/dev.doctree
docs/_build/doctrees/environment.pickle
docs/_build/doctrees/index.doctree
docs/_build/doctrees/installation.doctree
docs/_build/doctrees/ref.doctree
docs/_build/doctrees/tutorial-1-intro.doctree
docs/_build/doctrees/tutorial-2-assets.doctree
docs/_build/doctrees/tutorial-3-metadata.doctree
docs/_build/doctrees/tutorial-4-i18n.doctree
docs/_build/doctrees/tutorial.doctree
docs/_build/doctrees/_tutorial/1-intro/src/index.doctree
docs/_build/doctrees/_tutorial/2-assets/src/index.doctree
docs/_build/doctrees/_tutorial/3-metadata/src/index.doctree
docs/_build/html/.buildinfo
docs/_build/html/api.html
docs/_build/html/basics.html
docs/_build/html/changes.html
docs/_build/html/dev.html
docs/_build/html/genindex.html
docs/_build/html/index.html
docs/_build/html/installation.html
docs/_build/html/objects.inv
docs/_build/html/py-modindex.html
docs/_build/html/ref.html
docs/_build/html/search.html
docs/_build/html/searchindex.js
docs/_build/html/tutorial-1-intro.html
docs/_build/html/tutorial-2-assets.html
docs/_build/html/tutorial-3-metadata.html
docs/_build/html/tutorial-4-i18n.html
docs/_build/html/tutorial.html
docs/_build/html/_images/process.png
docs/_build/html/_sources/api.txt
docs/_build/html/_sources/basics.txt
docs/_build/html/_sources/changes.txt
docs/_build/html/_sources/dev.txt
docs/_build/html/_sources/index.txt
docs/_build/html/_sources/installation.txt
docs/_build/html/_sources/ref.txt
docs/_build/html/_sources/tutorial-1-intro.txt
docs/_build/html/_sources/tutorial-2-assets.txt
