Metadata-Version: 1.0
Name: Soho
Version: 0.8.0
Summary: A static web site generator
Home-page: http://readthedocs.org/projects/soho
Author: Damien Baty
Author-email: damien.baty.remove@gmail.com
License: UNKNOWN
Keywords: web static site generator
Platform: UNKNOWN
Classifier: Development Status :: 4 - Beta
Classifier: Environment :: Console
Classifier: Intended Audience :: Developers
Classifier: License :: OSI Approved :: BSD License
Classifier: Programming Language :: Python
Classifier: Programming Language :: Python :: 2.7
Classifier: Programming Language :: Python :: 3
Classifier: Programming Language :: Python :: 3.2
Classifier: Topic :: Internet :: WWW/HTTP
Classifier: Topic :: Text Processing :: Markup :: HTML
